rara_text_evaluator/__init__.py
rara_text_evaluator/exceptions.py
rara_text_evaluator/ngram_model_builder.py
rara_text_evaluator/quality_evaluator.py
rara_text_evaluator/utils.py
rara_text_evaluator/data/supported_build_languages.txt
rara_text_evaluator/models/text_validator_ngram_3_en.pkl
rara_text_evaluator/models/text_validator_ngram_3_et.pkl
rara_text_evaluator/models/text_validator_ngram_3_fallback.pkl
rara_text_evaluator-1.1.9.dist-info/licenses/LICENSE
rara_text_evaluator-1.1.9.dist-info/METADATA
rara_text_evaluator-1.1.9.dist-info/WHEEL
rara_text_evaluator-1.1.9.dist-info/top_level.txt
rara_text_evaluator-1.1.9.dist-info/RECORD
