Metadata-Version: 2.4
Name: rara-text-evaluator
Version: 1.1.9
Summary: Evaluate the quality of texts from a range of 0-1
License:                     GNU AFFERO GENERAL PUBLIC LICENSE
Classifier: Programming Language :: Python :: 3
Classifier: Programming Language :: Python :: 3.10
Classifier: Programming Language :: Python :: 3.11
Classifier: Programming Language :: Python :: 3.12
Classifier: Intended Audience :: Science/Research
Requires-Python: >=3.10
License-File: LICENSE
Requires-Dist: langdetect
Provides-Extra: testing
Requires-Dist: pytest>=8.0; extra == "testing"
Dynamic: license-file
